fw_gear_cow_says/__init__.py
fw_gear_cow_says/main.py
fw_gear_cow_says/parser.py
fw_gear_cow_says-2.3.4.dist-info/LICENSE
fw_gear_cow_says-2.3.4.dist-info/METADATA
fw_gear_cow_says-2.3.4.dist-info/WHEEL
fw_gear_cow_says-2.3.4.dist-info/RECORD
