Metadata-Version: 2.1
Name: fw-gear-cow-says
Version: 2.3.4
Summary: A gear that makes animal speak
Home-page: https://gitlab.com/flywheel-io/flywheel-apps/templates/poetry-cow-says
License: MIT
Keywords: Flywheel,Gears,Example
Author: Flywheel
Author-email: support@flywheel.io
Requires-Python: >=3.11,<4.0
Classifier: License :: OSI Approved :: MIT License
Classifier: Programming Language :: Python :: 3
Classifier: Programming Language :: Python :: 3.11
Classifier: Programming Language :: Python :: 3.12
Classifier: Topic :: Scientific/Engineering :: Medical Science Apps.
Requires-Dist: cowsay (>=3.0,<4.0)
Requires-Dist: flywheel-gear-toolkit (>=0.6,<0.7)
Requires-Dist: flywheel-sdk (>=18,<19)
Project-URL: Repository, https://gitlab.com/flywheel-io/flywheel-apps/templates/poetry-cow-says
